backtest/__init__.py
backtest/__main__.py
backtest/analyzer.py
backtest/broker.py
backtest/data.py
backtest/evaluator.py
backtest/fetcher.py
backtest/ledger.py
backtest/logging.json
backtest/main.py
backtest/router.py
backtest/version.py
backtest/exchanges/__init__.py
backtest/exchanges/korea_exchange.py
backtest/exchanges/kosdaq.py
backtest/exchanges/kospi.py
backtest/strategies/__init__.py
backtest/strategies/dummy.py
backtest/symbols/__init__.py
backtest/symbols/krx.py
backtest/utils/__init__.py
backtest/utils/korea_symbols.py
backtest/utils/symbols_krx.py
tests/__init__.py
tests/conftest.py
tests/test_analyzer.py
tests/test_broker.py
tests/test_evaluator.py
tests/test_fetcher.py
tests/test_ledger.py
tests/test_main.py
tests/test_order.py
tests/test_position.py
tests/test_router.py
tests/test_timeseries.py
tests/exchanges/__init__.py
tests/exchanges/test_korea_exchange.py
tests/markets/__init__.py
tests/markets/test_kosdaq.py
tests/markets/test_kospi.py
tests/strategies/__init__.py
tests/strategies/test_dummy.py
backtest-0.7.8.dist-info/LICENSE
backtest-0.7.8.dist-info/METADATA
backtest-0.7.8.dist-info/WHEEL
backtest-0.7.8.dist-info/entry_points.txt
backtest-0.7.8.dist-info/top_level.txt
backtest-0.7.8.dist-info/RECORD
